apnet/__init__.py
apnet-0.0.1.dist-info/LICENSE
apnet-0.0.1.dist-info/METADATA
apnet-0.0.1.dist-info/WHEEL
apnet-0.0.1.dist-info/top_level.txt
apnet-0.0.1.dist-info/RECORD
