Metadata-Version: 2.1
Name: apnet
Version: 0.0.1
Summary: Biblioteca Python para comunicação TCP entre Access Points (APs) com envio de arquivos e criptografia.
Author: Leonardo Nery
Author-email: leonardonery616@gmail.com
License: MIT
Requires-Python: >=3.10
License-File: LICENSE
Requires-Dist: cryptography >=41.0.0
